flytekitplugins_papermill-1.16.12-py3.14-nspkg.pth
flytekitplugins/papermill/__init__.py
flytekitplugins/papermill/task.py
flytekitplugins_papermill-1.16.12.dist-info/METADATA
flytekitplugins_papermill-1.16.12.dist-info/WHEEL
flytekitplugins_papermill-1.16.12.dist-info/namespace_packages.txt
flytekitplugins_papermill-1.16.12.dist-info/top_level.txt
flytekitplugins_papermill-1.16.12.dist-info/RECORD
